chk_args/__init__.py
chk_args/chk_args.py
chk_args-1.1.dist-info/METADATA
chk_args-1.1.dist-info/WHEEL
chk_args-1.1.dist-info/top_level.txt
chk_args-1.1.dist-info/RECORD
