Metadata-Version: 2.1
Name: chk-args
Version: 1.1
Summary: アノテーションチェッカー
Home-page: https://github.com/kurages/python_annotations_checker
Author: kurages
Author-email: kurages.dev@gmail.com
License: UNKNOWN
Project-URL: Bug Tracker, https://github.com/kurages/python_annotations_checker/issues
Platform: UNKNOWN
Classifier: Programming Language :: Python :: 3
Classifier: License :: OSI Approved :: MIT License
Classifier: Operating System :: OS Independent
Requires-Python: >=3.6
